Metadata-Version: 1.1
Name: onegov.municipality
Version: 1.0
Summary: UNKNOWN
Home-page: https://github.com/OneGov/onegov.municipality
Author: Verein OneGov
Author-email: mailto:info@4teamwork.ch
License: GPL2
Keywords: plone onegov municipality
Platform: UNKNOWN
Classifier: Programming Language :: Python
